lzhgripperwithforcesensor/__init__.py
lzhgripperwithforcesensor/app.py
lzhgripperwithforcesensor-0.1.8.dist-info/METADATA
lzhgripperwithforcesensor-0.1.8.dist-info/WHEEL
lzhgripperwithforcesensor-0.1.8.dist-info/top_level.txt
lzhgripperwithforcesensor-0.1.8.dist-info/RECORD
