Metadata-Version: 2.4
Name: lzhgripperwithforcesensor
Version: 0.1.8
Summary: An async TCP client wrapper for controlling a gripper with force sensing and callback support.
Author-email: lzh <zhhtdm@hotmail.com>
License: MIT
Project-URL: Homepage, https://github.com/zhhtdm/gripper-with-force-sensor
Project-URL: Repository, https://github.com/zhhtdm/gripper-with-force-sensor
Requires-Python: >=3.7
Requires-Dist: lzhasynctcpclient>=0.1.6
